dpo_reader/__init__.py
dpo_reader/audio.py
dpo_reader/cli.py
dpo_reader/discourse.py
dpo_reader/player.py
dpo_reader/tts/__init__.py
dpo_reader/tts/bark.py
dpo_reader/tts/base.py
dpo_reader/tts/openai.py
dpo_reader/tts/piper.py
dpo_reader/voices.py
dpo_reader-0.1.0.dist-info/WHEEL
dpo_reader-0.1.0.dist-info/entry_points.txt
dpo_reader-0.1.0.dist-info/METADATA
dpo_reader-0.1.0.dist-info/RECORD
