Metadata-Version: 2.3
Name: dpo-reader
Version: 0.1.0
Summary: Convert Discourse threads to multi-voice audio using TTS
Keywords: discourse,tts,text-to-speech,audio,bark,piper
Author: Jacob Coffee
Author-email: Jacob Coffee <jacob@z7x.org>
License: MIT
Classifier: Development Status :: 3 - Alpha
Classifier: Intended Audience :: Developers
Classifier: License :: OSI Approved :: MIT License
Classifier: Operating System :: OS Independent
Classifier: Programming Language :: Python :: 3.10
Classifier: Programming Language :: Python :: 3.11
Classifier: Programming Language :: Python :: 3.12
Classifier: Programming Language :: Python :: 3.13
Classifier: Programming Language :: Python :: 3 :: Only
Requires-Dist: httpx>=0.27
Requires-Dist: beautifulsoup4>=4.12
Requires-Dist: scipy>=1.11
Requires-Dist: numpy>=1.24
Requires-Dist: rich>=13.0
Requires-Dist: typer>=0.12
Requires-Dist: textual>=0.50
Requires-Dist: sounddevice>=0.4
Requires-Dist: bark>=0.1
Requires-Dist: dpo-reader[piper] ; extra == 'all'
Requires-Dist: piper-tts>=1.2 ; extra == 'piper'
Requires-Python: >=3.10, <3.14
Project-URL: Repository, https://github.com/JacobCoffee/dpo-reader
Project-URL: Documentation, https://jacobcoffee.github.io/dpo-reader
Project-URL: Issue Tracker, https://github.com/JacobCoffee/dpo-reader/issues
Provides-Extra: all
Provides-Extra: piper
